namecolors/__init__.py
namecolors/colors.py
namecolors/name.py
namecolors/data/get_data.py
namecolors-0.1.2.dist-info/METADATA
namecolors-0.1.2.dist-info/WHEEL
namecolors-0.1.2.dist-info/licenses/LICENSE.txt
namecolors-0.1.2.dist-info/RECORD
