Metadata-Version: 2.1
Name: namecolors
Version: 0.1.2
Summary: Get your colors name
Author-email: gunungpw <gunungpambudiw@gmail.com>
License-File: LICENSE.txt
Classifier: Programming Language :: Python :: 3
Classifier: Programming Language :: Python :: 3.8
Classifier: Programming Language :: Python :: 3.9
Classifier: Programming Language :: Python :: 3.10
Classifier: Programming Language :: Python :: 3.11
Classifier: Programming Language :: Python :: 3.12
Requires-Python: >=3.8
Requires-Dist: urllib3>=2.2.1
